realCfg/__init__.py
realCfg/cfg.py
realCfg/node.py
realCfg-1.0.0.dist-info/LICENSE
realCfg-1.0.0.dist-info/METADATA
realCfg-1.0.0.dist-info/WHEEL
realCfg-1.0.0.dist-info/top_level.txt
realCfg-1.0.0.dist-info/RECORD
